{
	"format_version": "1.8.0",
	"animations": {
		"animation.green_tordo.idle": {
			"loop": true,
			"animation_length": 1.5,
			"bones": {
				"Head": {
					"rotation": {
						"0.0": [0, 0, 0],
						"0.75": [5, 0, 0],
						"1.5": [0, 0, 0]
					}
				},
				"RightArm": {
					"rotation": {
						"0.0": [0, 0, 0],
						"0.75": [0, 0, 2.5],
						"1.5": [0, 0, 0]
					}
				},
				"LeftArm": {
					"rotation": {
						"0.0": [0, 0, 0],
						"0.75": [0, 0, -2.5],
						"1.5": [0, 0, 0]
					}
				}
			}
		},
		"animation.green_tordo.walk": {
			"loop": true,
			"animation_length": 1.5,
			"bones": {
				"Head": {
					"rotation": {
						"0.0": [0, 0, 0],
						"0.75": [5, 0, 0],
						"1.5": [0, 0, 0]
					}
				},
				"RightArm": {
					"rotation": {
						"0.0": [0, 0, 0],
						"0.375": [-10, 0, 0],
						"1.0833": [10, 0, 0],
						"1.5": [0, 0, 0]
					}
				},
				"LeftArm": {
					"rotation": {
						"0.0": [0, 0, 0],
						"0.375": [10, 0, 0],
						"1.0833": [-10, 0, 0],
						"1.5": [0, 0, 0]
					}
				},
				"RightLeg": {
					"rotation": {
						"0.0": [0, 0, 0],
						"0.375": [10, 0, 0],
						"1.0833": [-10, 0, 0],
						"1.5": [0, 0, 0]
					}
				},
				"LeftLeg": {
					"rotation": {
						"0.0": [0, 0, 0],
						"0.375": [-10, 0, 0],
						"1.0833": [10, 0, 0],
						"1.5": [0, 0, 0]
					}
				}
			}
		}
	}
}