{
  "temperature": 0.8,
  "downfall": 0.4,
  "precipitation": "none",
  "effects": {
    "sky_color": 1927192,
    "fog_color": 1524224,
    "water_color": 3496974,
    "water_fog_color": 3496974,
    "grass_color": 800769,
    "foliage_color": 800769
  },
  "spawners": {},
  "spawn_costs": {},
  "carvers": {},
  "features": [
    [
      "jitl:orbadite_ore",
      "jitl:gorbite_ore",
      "jitl:corba_veg",
      "jitl:corba_tree_small",
      "jitl:corba_tree_medium",
      "jitl:corba_tree_large"
    ]
  ]
}
